flit_bumpversion/__init__.py
flit_bumpversion/__main__.py
flit_bumpversion/utils.py
flit_bumpversion-0.0.7.dist-info/entry_points.txt
flit_bumpversion-0.0.7.dist-info/LICENSE
flit_bumpversion-0.0.7.dist-info/WHEEL
flit_bumpversion-0.0.7.dist-info/METADATA
flit_bumpversion-0.0.7.dist-info/RECORD
